circlecitest/main.py
circlecitest/tests/test_main.py
circlecitest-0.1.0.dist-info/WHEEL
circlecitest-0.1.0.dist-info/METADATA
circlecitest-0.1.0.dist-info/RECORD
