Metadata-Version: 2.1
Name: circlecitest
Version: 0.1.0
Summary: testing pypi deploy
Home-page: UNKNOWN
License: UNKNOWN
Author: ape364
Author-email: ape364@gmail.com
Requires-Python: >=3.7,<4.0
Classifier: Programming Language :: Python :: 3
Classifier: Programming Language :: Python :: 3.7
Requires-Dist: aiohttp (>=3.5,<4.0)
